pygifconvert_test_mrvko/__init__.py
pygifconvert_test_mrvko/converter.py
pygifconvert_test_mrvko-1.0.1.dist-info/LICENSE
pygifconvert_test_mrvko-1.0.1.dist-info/METADATA
pygifconvert_test_mrvko-1.0.1.dist-info/WHEEL
pygifconvert_test_mrvko-1.0.1.dist-info/top_level.txt
pygifconvert_test_mrvko-1.0.1.dist-info/RECORD
